{
  "date": "2026-06-22",
  "data": [
    {
      "eps": "N/A",
      "surprise": "N/A",
      "time": "time-not-supplied",
      "symbol": "WDS",
      "name": "Woodside Energy Group Limited",
      "marketCap": "$38,117,057,867",
      "fiscalQuarterEnding": "Mar/2026",
      "epsForecast": "",
      "noOfEsts": "2"
    },
    {
      "eps": "($3.72)",
      "surprise": "-4033.33",
      "time": "time-not-supplied",
      "symbol": "FRVO",
      "name": "Fervo Energy Company",
      "marketCap": "$9,950,202,265",
      "fiscalQuarterEnding": "Mar/2026",
      "epsForecast": "($0.09)",
      "noOfEsts": "2"
    },
    {
      "eps": "($0.45)",
      "surprise": "-800",
      "time": "time-not-supplied",
      "symbol": "HAWK",
      "name": "HawkEye 360, Inc.",
      "marketCap": "$2,131,515,329",
      "fiscalQuarterEnding": "Mar/2026",
      "epsForecast": "($0.05)",
      "noOfEsts": "2"
    },
    {
      "eps": "$0.39",
      "surprise": "N/A",
      "time": "time-not-supplied",
      "symbol": "EBF",
      "name": "Ennis, Inc.",
      "marketCap": "$514,313,870",
      "fiscalQuarterEnding": "May/2026",
      "epsForecast": "",
      "noOfEsts": "N/A"
    },
    {
      "eps": "($0.03)",
      "surprise": "-50",
      "time": "time-not-supplied",
      "symbol": "POWW",
      "name": "Outdoor Holding Company",
      "marketCap": "$250,997,865",
      "fiscalQuarterEnding": "Mar/2026",
      "epsForecast": "($0.02)",
      "noOfEsts": "1"
    },
    {
      "eps": "N/A",
      "surprise": "N/A",
      "time": "time-not-supplied",
      "symbol": "MOB",
      "name": "Mobilicom Limited",
      "marketCap": "$71,883,881",
      "fiscalQuarterEnding": "Mar/2026",
      "epsForecast": "",
      "noOfEsts": "2"
    },
    {
      "eps": "($0.44)",
      "surprise": "N/A",
      "time": "time-not-supplied",
      "symbol": "ATLN",
      "name": "Atlantic International Corp.",
      "marketCap": "$41,955,236",
      "fiscalQuarterEnding": "Mar/2026",
      "epsForecast": "",
      "noOfEsts": "N/A"
    },
    {
      "eps": "N/A",
      "surprise": "N/A",
      "time": "time-not-supplied",
      "symbol": "GNS",
      "name": "Genius Group Limited",
      "marketCap": "$40,551,468",
      "fiscalQuarterEnding": "Mar/2026",
      "epsForecast": "",
      "noOfEsts": "2"
    },
    {
      "eps": "N/A",
      "surprise": "N/A",
      "time": "time-not-supplied",
      "symbol": "RYOJ",
      "name": "rYojbaba Co., Ltd.",
      "marketCap": "$27,951,000",
      "fiscalQuarterEnding": "Mar/2026",
      "epsForecast": "",
      "noOfEsts": "2"
    },
    {
      "eps": "($0.24)",
      "surprise": "N/A",
      "time": "time-not-supplied",
      "symbol": "VSTD",
      "name": "Vestand Inc. ",
      "marketCap": "$2,987,246",
      "fiscalQuarterEnding": "Mar/2026",
      "epsForecast": "",
      "noOfEsts": "2"
    },
    {
      "eps": "($3.38)",
      "surprise": "N/A",
      "time": "time-not-supplied",
      "symbol": "IVF",
      "name": "INVO Fertility, Inc.",
      "marketCap": "$2,679,053",
      "fiscalQuarterEnding": "Mar/2026",
      "epsForecast": "",
      "noOfEsts": "N/A"
    },
    {
      "eps": "N/A",
      "surprise": "N/A",
      "time": "time-not-supplied",
      "symbol": "IMTE",
      "name": "Integrated Media Technology Limited",
      "marketCap": "$1,765,953",
      "fiscalQuarterEnding": "Mar/2026",
      "epsForecast": "",
      "noOfEsts": "2"
    }
  ]
}